{
  "version": 1,
  "base_track": "「１」",
  "base_artist": "日野森志歩",
  "createdAt": "2026-03-04T11:24:20.752704Z",
  "candidates": [
    {
      "id": "lrclib_1",
      "source": "lrclib",
      "title": "１・２・３ - 1 2 3",
      "artist": "After the Rain",
      "has_synced": true,
      "path": "select/01_1・2・3_-_1_2_3_After_the_Rain.lrc"
    },
    {
      "id": "lrclib_2",
      "source": "lrclib",
      "title": "１・２・３",
      "artist": "After the Rain",
      "has_synced": true,
      "path": "select/02_1・2・3_After_the_Rain.lrc"
    },
    {
      "id": "lrclib_3",
      "source": "lrclib",
      "title": "１（TV EDIT)",
      "artist": "MOB CHOIR",
      "has_synced": false,
      "path": "select/03_1(TV_EDIT)_MOB_CHOIR.txt"
    },
    {
      "id": "lrclib_4",
      "source": "lrclib",
      "title": "１・２・３ (Paused)",
      "artist": "After the Rain",
      "has_synced": true,
      "path": "select/04_1・2・3_(Paused)_After_the_Rain.lrc"
    },
    {
      "id": "lrclib_5",
      "source": "lrclib",
      "title": "１％通行",
      "artist": "Sanso Nakamura",
      "has_synced": false,
      "path": "select/05_1_通行_Sanso_Nakamura.txt"
    },
    {
      "id": "lrclib_6",
      "source": "lrclib",
      "title": "冬眠 (１.３X)",
      "artist": "小飞机",
      "has_synced": false,
      "path": "select/06_冬眠_(1.3X)_小飞机.txt"
    },
    {
      "id": "lrclib_7",
      "source": "lrclib",
      "title": "１．ご挨拶。そして、性処理フェラ",
      "artist": "sikopaper",
      "has_synced": true,
      "path": "select/07_1.ご挨拶。そして、性処理フェラ_sikopaper.lrc"
    },
    {
      "id": "lrclib_8",
      "source": "lrclib",
      "title": "１_勇者様お帰りなさいセックス（シスター中心）",
      "artist": "しゃーぷ",
      "has_synced": true,
      "path": "select/08_1_勇者様お帰りなさいセックス(シスター中心)_しゃーぷ.lrc"
    },
    {
      "id": "lrclib_9",
      "source": "lrclib",
      "title": "１，オッパブでまさかの親友彼女と…",
      "artist": "あまとろすいーつ",
      "has_synced": true,
      "path": "select/09_1,オッパブでまさかの親友彼女と..._あまとろすいーつ.lrc"
    },
    {
      "id": "lrclib_10",
      "source": "lrclib",
      "title": "１，清楚なメイドは調教済み",
      "artist": "あまとろすいーつ",
      "has_synced": true,
      "path": "select/10_1,清楚なメイドは調教済み_あまとろすいーつ.lrc"
    },
    {
      "id": "lrclib_11",
      "source": "lrclib",
      "title": "１．ご挨拶。そして、性処理フェラ_SEなし",
      "artist": "sikopaper",
      "has_synced": true,
      "path": "select/11_1.ご挨拶。そして、性処理フェラ_SEなし_sikopaper.lrc"
    },
    {
      "id": "lrclib_12",
      "source": "lrclib",
      "title": "【１】冒険前日の酒場で…（プロローグ）",
      "artist": "脳とりがー",
      "has_synced": true,
      "path": "select/12_【1】冒険前日の酒場で...(プロローグ)_脳とりがー.lrc"
    },
    {
      "id": "lrclib_13",
      "source": "lrclib",
      "title": "【１】「Level.01」（導入、耳舐め）",
      "artist": "シロイルカ",
      "has_synced": true,
      "path": "select/13_【1】「Level.01」(導入、耳舐め)_シロイルカ.lrc"
    },
    {
      "id": "lrclib_14",
      "source": "lrclib",
      "title": "【１】僕の後輩は、なんだかちょっとおかしい。",
      "artist": "シロイルカ",
      "has_synced": true,
      "path": "select/14_【1】僕の後輩は、なんだかちょっとおかしい。_シロイルカ.lrc"
    },
    {
      "id": "lrclib_15",
      "source": "lrclib",
      "title": "【１】どんな人でも、催眠にかかることは可能であるという証明",
      "artist": "空心菜館",
      "has_synced": true,
      "path": "select/15_【1】どんな人でも、催眠にかかることは可能であるという証明_空心菜館.lrc"
    },
    {
      "id": "lrclib_16",
      "source": "lrclib",
      "title": "【１】分裂した世界で（冒頭、催眠・耳舐め）",
      "artist": "空心菜館",
      "has_synced": true,
      "path": "select/16_【1】分裂した世界で(冒頭、催眠・耳舐め)_空心菜館.lrc"
    },
    {
      "id": "petitlyrics_1",
      "source": "petitlyrics",
      "title": "「1」",
      "artist": "日野森志歩",
      "has_synced": false,
      "path": "select/pl_01_「1」_日野森志歩.txt"
    }
  ]
}